CHANGELOG.md
LICENSE
MANIFEST.in
README.md
requirements.dev.txt
requirements.txt
setup.cfg
setup.py
data/example.cfg
docs/soft_deleted/soft_deleted_doc.md
pik/__init__.py
pik/core/__init__.py
pik/core/cache.py
pik/core/clear_history/__init__.py
pik/core/clear_history/tasks.py
pik/core/clear_history/management/__init__.py
pik/core/clear_history/management/commands/__init__.py
pik/core/clear_history/management/commands/clear_history.py
pik/core/models/__init__.py
pik/core/models/_collector_delete.py
pik/core/models/base.py
pik/core/models/dated.py
pik/core/models/historized.py
pik/core/models/owned.py
pik/core/models/soft_deleted.py
pik/core/models/uided.py
pik/core/models/versioned.py
pik/core/models/fields/__init__.py
pik/core/models/fields/inheritance.py
pik/core/shortcuts/__init__.py
pik/core/shortcuts/model_objects.py
pik/core/shortcuts/request.py
pik/core/tests/__init__.py
pik/core/tests/fixtures.py
pik/libs/__init__.py
pik/utils/__init__.py
pik/utils/normalization.py
pik_django_utils.egg-info/PKG-INFO
pik_django_utils.egg-info/SOURCES.txt
pik_django_utils.egg-info/dependency_links.txt
pik_django_utils.egg-info/requires.txt
pik_django_utils.egg-info/top_level.txt
test_core_models/__init__.py
test_core_models/models/__init__.py
test_core_models/models/base.py
test_core_models/models/dated.py
test_core_models/models/historized.py
test_core_models/models/owned.py
test_core_models/models/soft_deleted1.py
test_core_models/models/soft_deleted2.py
test_core_models/models/soft_deleted3.py
test_core_models/models/uided.py
test_core_models/models/versioned.py
test_core_models/tests/__init__.py
test_core_models/tests/factories.py
test_core_models/tests/test_models_base.py
test_core_models/tests/test_models_dated.py
test_core_models/tests/test_models_historized.py
test_core_models/tests/test_models_owned.py
test_core_models/tests/test_models_soft_deleted1.py
test_core_models/tests/test_models_soft_deleted2.py
test_core_models/tests/test_models_soft_deleted3.py
test_core_models/tests/test_models_uided.py
test_core_models/tests/test_models_versioned.py
test_core_models_fields/__init__.py
test_core_models_fields/models/__init__.py
test_core_models_fields/models/base.py
