Metadata-Version: 2.1
Name: pik-django-utils
Version: 2.1.0
Summary: Common PIK Django utils and tools
Home-page: https://github.com/pik-software/pik-django-utils
Author: pik-software
Author-email: no-reply@pik-software.ru
License: UNKNOWN
Project-URL: Bug Reports, https://github.com/pik-software/pik-django-utils/issues
Project-URL: Funding, https://github.com/pik-software/pik-django-utils
Project-URL: Say Thanks!, https://saythanks.io/to/pik_software
Project-URL: Source, https://github.com/pik-software/pik-django-utils
Keywords: pik django
Platform: UNKNOWN
Classifier: Development Status :: 5 - Production/Stable
Classifier: Intended Audience :: Developers
Classifier: Topic :: Software Development :: Build Tools
Classifier: License :: OSI Approved :: MIT License
Classifier: Programming Language :: Python :: 3.6
Requires-Python: ~=3.6
Provides-Extra: dev
License-File: LICENSE
